spectre/__init__.py
spectre/model.py
spectre/configs/__init__.py
spectre/configs/accelerate_default.yaml
spectre/configs/dino_default.yaml
spectre/configs/dinov2_default.yaml
spectre/configs/mae_default.yaml
spectre/configs/siglip_default.yaml
spectre/configs/total_segmentator.yaml
spectre/data/__init__.py
spectre/data/_base_datasets.py
spectre/data/abdomen_atlas.py
spectre/data/abdomenct_1k.py
spectre/data/amos.py
spectre/data/ct_rate.py
spectre/data/inspect.py
spectre/data/merlin.py
spectre/data/nlst.py
spectre/data/panorama.py
spectre/data/sinoct.py
spectre/data/total_segmentator.py
spectre/losses/__init__.py
spectre/losses/mask_classification_loss.py
spectre/models/__init__.py
spectre/models/eomt.py
spectre/models/resnet.py
spectre/models/seomt.py
spectre/models/upsample_anything.py
spectre/models/vision_transformer.py
spectre/models/vision_transformer_features.py
spectre/models/layers/__init__.py
spectre/models/layers/attention.py
spectre/models/layers/layernorm.py
spectre/models/layers/patch_embed.py
spectre/models/layers/rotary_pos_embed.py
spectre/ssl/__init__.py
spectre/ssl/frameworks/__init__.py
spectre/ssl/frameworks/contrastive.py
spectre/ssl/frameworks/generative.py
spectre/ssl/frameworks/vision_language.py
spectre/ssl/heads/__init__.py
spectre/ssl/heads/dino_head.py
spectre/ssl/heads/siglip_head.py
spectre/ssl/losses/__init__.py
spectre/ssl/losses/_center.py
spectre/ssl/losses/dino_loss.py
spectre/ssl/losses/gram_loss.py
spectre/ssl/losses/ibot_loss.py
spectre/ssl/losses/koleo_loss.py
spectre/ssl/losses/siglip_loss.py
spectre/ssl/models/__init__.py
spectre/ssl/models/mae_decoder.py
spectre/ssl/models/masked_vit.py
spectre/ssl/transforms/__init__.py
spectre/ssl/transforms/dino_transform.py
spectre/ssl/transforms/mae_transform.py
spectre/ssl/transforms/siglip_transform.py
spectre/transforms/__init__.py
spectre/transforms/combine_labels.py
spectre/transforms/generate_report.py
spectre/transforms/largest_multiple_crop.py
spectre_fm-0.1.1.dist-info/licenses/LICENSE
spectre_fm-0.1.1.dist-info/licenses/LICENSE_MODELS
spectre_fm-0.1.1.dist-info/METADATA
spectre_fm-0.1.1.dist-info/WHEEL
spectre_fm-0.1.1.dist-info/top_level.txt
spectre_fm-0.1.1.dist-info/RECORD
