Metadata-Version: 2.4
Name: spectre-fm
Version: 0.1.1
Summary: SPECTRE: cross-modal self-supervised pretraining for CT representation extraction
Author-email: Cris Claessens <c.h.b.claessens@tue.nl>, Christiaan Viviers <c.g.a.viviers@tue.nl>
Project-URL: Homepage, https://github.com/cclaess/SPECTRE
Project-URL: Source, https://github.com/cclaess/SPECTRE
Project-URL: BugTracker, https://github.com/cclaess/SPECTRE/issues
Keywords: medical,ct,self-supervised,vision,deep-learning
Classifier: Programming Language :: Python :: 3.8
Classifier: Programming Language :: Python :: 3.9
Classifier: Programming Language :: Python :: 3.10
Classifier: Programming Language :: Python :: 3.11
Classifier: Operating System :: OS Independent
Classifier: Topic :: Scientific/Engineering :: Artificial Intelligence
Requires-Python: >=3.8
License-File: LICENSE
License-File: LICENSE_MODELS
Requires-Dist: torch
Requires-Dist: wandb
Requires-Dist: numpy
Requires-Dist: monai[all]
Requires-Dist: nibabel
Requires-Dist: SimpleITK
Requires-Dist: timm
Requires-Dist: scipy
Requires-Dist: pandas
Requires-Dist: openpyxl
Requires-Dist: accelerate
Requires-Dist: omegaconf
Requires-Dist: transformers
Requires-Dist: tokenizers
Requires-Dist: peft
Requires-Dist: loralib
Requires-Dist: matplotlib
Requires-Dist: seaborn
Requires-Dist: scikit-learn
Requires-Dist: umap-learn
Dynamic: license-file
